thingsboard_gateway/__init__.py
thingsboard_gateway/tb_gateway.py
thingsboard_gateway/config/bacnet.json
thingsboard_gateway/config/ble.json
thingsboard_gateway/config/can.json
thingsboard_gateway/config/connected_devices.json
thingsboard_gateway/config/custom_serial.json
thingsboard_gateway/config/ftp.json
thingsboard_gateway/config/grpc_connector_1.json
thingsboard_gateway/config/logs.conf
thingsboard_gateway/config/modbus.json
thingsboard_gateway/config/modbus_serial.json
thingsboard_gateway/config/mqtt.json
thingsboard_gateway/config/mqtt_custom.json
thingsboard_gateway/config/new_modbus.json
thingsboard_gateway/config/odbc.json
thingsboard_gateway/config/opcua.json
thingsboard_gateway/config/request.json
thingsboard_gateway/config/rest.json
thingsboard_gateway/config/snmp.json
thingsboard_gateway/config/snmp_custom.json
thingsboard_gateway/config/socket.json
thingsboard_gateway/config/tb_gateway.yaml
thingsboard_gateway/connectors/__init__.py
thingsboard_gateway/connectors/connector.py
thingsboard_gateway/connectors/converter.py
thingsboard_gateway/connectors/bacnet/__init__.py
thingsboard_gateway/connectors/bacnet/bacnet_connector.py
thingsboard_gateway/connectors/bacnet/bacnet_converter.py
thingsboard_gateway/connectors/bacnet/bacnet_downlink_converter.py
thingsboard_gateway/connectors/bacnet/bacnet_uplink_converter.py
thingsboard_gateway/connectors/bacnet/bacnet_utilities/__init__.py
thingsboard_gateway/connectors/bacnet/bacnet_utilities/tb_gateway_bacnet_application.py
thingsboard_gateway/connectors/bacnet/bacnet_utilities/tb_gateway_bacnet_device.py
thingsboard_gateway/connectors/ble/__init__.py
thingsboard_gateway/connectors/ble/ble_connector.py
thingsboard_gateway/connectors/ble/ble_uplink_converter.py
thingsboard_gateway/connectors/ble/bytes_ble_uplink_converter.py
thingsboard_gateway/connectors/ble/device.py
thingsboard_gateway/connectors/ble/error_handler.py
thingsboard_gateway/connectors/can/__init__.py
ndu_gateway-2.6.7.1.dist-info/LICENSE
ndu_gateway-2.6.7.1.dist-info/METADATA
ndu_gateway-2.6.7.1.dist-info/WHEEL
ndu_gateway-2.6.7.1.dist-info/entry_points.txt
ndu_gateway-2.6.7.1.dist-info/top_level.txt
ndu_gateway-2.6.7.1.dist-info/RECORD
